<?xml version="1.0" encoding="UTF-8" standalone="no" ?>
<files>

  <version>1.0.0</version>

  <file hash="" localdate="" serverdate="" versionId="">catalog.zip</file>

  <file hash="9bebbba2e0c891a25624bce97189b98768df0edc" localdate="20201024171449" serverdate="2016/07/13 14:55:10" versionId="vE4UFupik2vGw6kdOEl8O0Tw.mxP7CAv">data/material.pose</file>

  <file hash="" localdate="" serverdate="" versionId="">externalLink</file>

  <file hash="a0d44832e163997f654a5bc09440161d93c73a99" localdate="20201024171450" serverdate="2016/07/13 14:55:10" versionId="beOOLBKI1mzsWjV0eFXZpKh_LMhZgEsR">icedata/layerData.xml</file>

  <file hash="" localdate="" serverdate="" versionId="">info.zip</file>

  <file hash="" localdate="" serverdate="" versionId="">modifiedData</file>

  <file hash="24c8807dc21f66f7d2c5596070453353417d916d" localdate="20201024171450" serverdate="2016/07/13 14:55:10" versionId="9IQykAeLcbkO_MV2c7ClJEjiL8JV6iJu">thumbnail/thumbnail.png</file>

</files>
