<?xml version="1.0" encoding="UTF-8" standalone="no" ?>
<files>

  <version>1.0.0</version>

  <file hash="dc37e1105bf044062cf426c43d9a164bf887f36d" localdate="20201025161914" serverdate="2020/07/18 12:55:03" versionId="ZWhY8SZ7KEn0xkNGRpCziWieQa4DX5sw">catalog.zip</file>

  <file hash="f1085283d55a46370663172382554235a927a914" localdate="20201025161858" serverdate="2020/07/18 12:55:03" versionId="MgZ9KKCKQHhxYa51jqG6Svq2XtKgd4zV">data/material_0.layer</file>

  <file hash="" localdate="" serverdate="" versionId="">externalLink</file>

  <file hash="45c02c2ecc36d7f27a10820b870e1cf0c64c3412" localdate="20201025161903" serverdate="2020/07/18 12:55:03" versionId="SmTLPwePybLE6pipQrwc66RFcAYQC4qv">icedata/layerData.xml</file>

  <file hash="c20c7bc9867202c9ab3eccc2e408d14e4c26dd37" localdate="20201025161914" serverdate="2020/07/18 12:55:03" versionId="88Uea3xwoJMhfHkRdJPJFLzP4Y.O1DuE">info.zip</file>

  <file hash="" localdate="" serverdate="" versionId="">modifiedData</file>

  <file hash="b1bba992fde39a6f4de1f00f5cd916fcd1460f3a" localdate="20201025161914" serverdate="2020/07/18 12:55:03" versionId="11zDG.P_TyVpJDgsL0Ooe6p3IxUgL4Eb">thumbnail/thumbnail.png</file>

</files>
