<?xml version="1.0" encoding="UTF-8" standalone="no" ?>
<archive>

  <version>2.0.8</version>

  <catalog modify_description="0" modify_info="0" modify_name="0" modify_thumbnail="0" uuid="20719482bd-f311-dda7-3cf4-fb700d07bd">
    <type>material</type>
    <readonly>0</readonly>
    <share_edit_flag>0</share_edit_flag>
    <uploadable>1</uploadable>
    <tool company="celsys" name="paint" version="1.10.5"/>
    <name>Sampled Brush 2</name>
    <groups>
      <group modify_description="0" modify_info="0" modify_name="0" modify_thumbnail="0" parentuuid="" uuid="47a219dcd9-fa4b-d08f-1b57-98585b1922">
        <tool company="celsys" name="paint" version="1.10.5"/>
        <type ver="1.0.0">material</type>
        <name></name>
        <required>0</required>
        <reserveId>0</reserveId>
        <reserveWait>0</reserveWait>
        <items>
          <item modify_description="0" modify_info="0" modify_name="0" modify_thumbnail="0" parentuuid="" uuid="1dee069f47-2649-cda9-49cc-654fe0bdc1">
            <tool company="celsys" name="paint" version="1.10.5"/>
            <type ver="1.0.1">image</type>
            <name>Sampled Brush 2</name>
            <created_date>2020/12/14 01:28:32</created_date>
            <modified_date>2020/12/14 01:28:32</modified_date>
            <required>0</required>
            <permittool>
              <cspdebut>1</cspdebut>
            </permittool>
            <reserveId>0</reserveId>
            <reserveWait>0</reserveWait>
            <thumbnail>
              <fileref idref="5f3b54e128-1240-5e95-dd2d-368bd0b050"/>
            </thumbnail>
            <data>
              <fileref idref="bbfcf67f95-2641-f987-4ec5-b3c6cdfa92"/>
            </data>
            <icedata>
              <fileref idref="4613b9f4eb-7d48-b1bd-7d6c-b4b77c02a6"/>
            </icedata>
          </item>
        </items>
      </group>
    </groups>
    <region/>
  </catalog>

  <files>
    <file document="false" encrypt="false" id="4613b9f4eb-7d48-b1bd-7d6c-b4b77c02a6" mime="text/xml">
      <path>icedata/layerData.xml</path>
    </file>
    <file document="false" encrypt="false" id="5f3b54e128-1240-5e95-dd2d-368bd0b050" mime="image/png">
      <path>thumbnail/thumbnail.png</path>
    </file>
    <file document="false" encrypt="true" id="bbfcf67f95-2641-f987-4ec5-b3c6cdfa92" mime="application/octet-stream">
      <path>data/material_0.layer</path>
    </file>
  </files>

</archive>
