<?xml version="1.0" encoding="UTF-8" standalone="no" ?>
<cloud>

  <version>1.0.0</version>

  <name>梅</name>

  <cloudcontentid>358</cloudcontentid>

  <revision>1</revision>

  <key>bd521e14c5-504e-30b5-a6f1-cb8bbde199</key>

  <contenttype>material</contenttype>

  <contentsubtype>image</contentsubtype>

  <thumbnailurl></thumbnailurl>

  <subpath>Paint004</subpath>

  <basePath>installation_material/58/03/358</basePath>

  <size>151736</size>

  <permit>1</permit>

  <husk>0</husk>

  <owner>9114</owner>

  <acl></acl>

  <createdat>2016-07-13 14:48:58</createdat>

  <updatedat>2016-07-13 14:49:01</updatedat>

  <dataVersion>2.0.0</dataVersion>

  <ownerhistory/>

  <teamNameList/>

</cloud>
