<?xml version="1.0" encoding="UTF-8" standalone="no" ?>
<cloud>

  <version>1.0.0</version>

  <name>MM11-マンション15</name>

  <cloudcontentid>866</cloudcontentid>

  <revision>1</revision>

  <key>c805b55662-1c43-d18c-ae2c-61903aaa9d</key>

  <contenttype>material</contenttype>

  <contentsubtype>image</contentsubtype>

  <thumbnailurl></thumbnailurl>

  <subpath>Paint009</subpath>

  <basePath>installation_material/66/08/866</basePath>

  <size>1170632</size>

  <permit>0</permit>

  <husk>1</husk>

  <owner>9114</owner>

  <acl></acl>

  <createdat>2016-07-13 15:25:15</createdat>

  <updatedat>2016-07-13 15:25:18</updatedat>

  <dataVersion>2.0.0</dataVersion>

  <ownerhistory/>

  <teamNameList/>

</cloud>
