<?xml version="1.0" encoding="UTF-8" standalone="no" ?>
<files>

  <version>1.0.0</version>

  <file hash="" localdate="" serverdate="" versionId="">catalog.zip</file>

  <file hash="f915fef7e2e36664deb938f958dc845303cb1c86" localdate="20201024163429" serverdate="2016/07/13 14:59:58" versionId=".YBcfUcijhaphiSWCaO6LC6c5XpIcZcq">data/material.layer</file>

  <file hash="" localdate="" serverdate="" versionId="">externalLink</file>

  <file hash="100e54b29ddcbe278a64c1a46676c87acb02766f" localdate="20201024163429" serverdate="2016/07/13 14:59:58" versionId="B__1TtnZaDv9ndslcqCWRQ.MVWWj0_KW">icedata/layerData.xml</file>

  <file hash="" localdate="" serverdate="" versionId="">info.zip</file>

  <file hash="" localdate="" serverdate="" versionId="">modifiedData</file>

  <file hash="4b61db84c64efe41c59668b613b276af939ca750" localdate="20201024163430" serverdate="2016/07/13 14:59:58" versionId="BRpqLq3DdRSGEAjQCpnPoWpoI5Tty7Ot">thumbnail/thumbnail.png</file>

</files>
