<?xml version="1.0" encoding="UTF-8" standalone="no" ?>
<archive>

  <version>2.0.0</version>

  <catalog modify_description="0" modify_info="0" modify_name="0" modify_thumbnail="0" uuid="74e25b7f6c-3e4a-2e99-5df9-30df33f5f1">
    <type>material</type>
    <readonly>1</readonly>
    <share_edit_flag>0</share_edit_flag>
    <uploadable>0</uploadable>
    <tool company="celsys" name="paint" version="1.1.0"/>
    <name>MM11-house 06</name>
    <groups>
      <group modify_description="0" modify_info="0" modify_name="0" modify_thumbnail="0" parentuuid="" uuid="e402dc01de-9c40-ad8b-3bf0-905229b50b">
        <tool company="celsys" name="paint" version="1.1.0"/>
        <type ver="1.0.0">material</type>
        <name></name>
        <required>0</required>
        <reserveId>0</reserveId>
        <reserveWait>0</reserveWait>
        <items>
          <item modify_description="0" modify_info="0" modify_name="0" modify_thumbnail="0" parentuuid="" uuid="351966e067-5941-dd9d-bb25-af5f31ee73">
            <tool company="celsys" name="paint" version="1.1.0"/>
            <type ver="1.0.0">image</type>
            <name>MM11-house 06</name>
            <created_date>2016/06/21 10:07:44</created_date>
            <modified_date>2016/06/21 10:07:44</modified_date>
            <required>0</required>
            <permittool>
              <cspdebut>1</cspdebut>
            </permittool>
            <reserveId>0</reserveId>
            <reserveWait>0</reserveWait>
            <thumbnail>
              <fileref idref="b111eb88ae-0d43-6591-f986-4321aeb6ae"/>
            </thumbnail>
            <data>
              <fileref idref="1b8de2fb87-ff45-9484-c246-11c636b1eb"/>
            </data>
            <icedata>
              <fileref idref="01726eb092-4946-b7ab-c951-233d723f15"/>
            </icedata>
          </item>
        </items>
      </group>
    </groups>
    <region/>
  </catalog>

  <files>
    <file document="false" encrypt="false" id="01726eb092-4946-b7ab-c951-233d723f15" mime="text/xml">
      <path>icedata/layerData.xml</path>
    </file>
    <file document="false" encrypt="true" id="1b8de2fb87-ff45-9484-c246-11c636b1eb" mime="application/octet-stream">
      <path>data/material.layer</path>
    </file>
    <file document="false" encrypt="false" id="b111eb88ae-0d43-6591-f986-4321aeb6ae" mime="image/png">
      <path>thumbnail/thumbnail.png</path>
    </file>
  </files>

</archive>
