<?xml version="1.0" encoding="UTF-8" standalone="no" ?>
<files>

  <version>1.0.0</version>

  <file hash="" localdate="" serverdate="" versionId="">catalog.zip</file>

  <file hash="148960c126e9393830a1c6bdf9b18282866fe9af" localdate="20201024162642" serverdate="2016/07/13 14:38:33" versionId="">data/material.layer</file>

  <file hash="" localdate="" serverdate="" versionId="">externalLink</file>

  <file hash="f624dfcad9876547ca13d146027c2c6af835f436" localdate="20201024162642" serverdate="2016/07/13 14:38:33" versionId="">icedata/layerData.xml</file>

  <file hash="" localdate="" serverdate="" versionId="">info.zip</file>

  <file hash="" localdate="" serverdate="" versionId="">modifiedData</file>

  <file hash="581016e806dbad05aee6fc91ed901d79a3ea66cc" localdate="20201024162643" serverdate="2016/07/13 14:38:33" versionId="">thumbnail/thumbnail.png</file>

</files>
