<?xml version="1.0" encoding="UTF-8" standalone="no" ?>
<cloud>

  <version>1.0.0</version>

  <name>_Stroke006</name>

  <cloudcontentid>123408853</cloudcontentid>

  <revision>1</revision>

  <key>6fedb7f1c5-7942-80bf-b009-c3b0084e53</key>

  <contenttype>material</contenttype>

  <contentsubtype>image</contentsubtype>

  <thumbnailurl></thumbnailurl>

  <subpath>00/15</subpath>

  <basePath></basePath>

  <size>466744</size>

  <permit>1</permit>

  <husk>0</husk>

  <owner>919503</owner>

  <acl></acl>

  <createdat>2021-01-01 09:14:12</createdat>

  <updatedat>2021-01-01 09:14:31</updatedat>

  <dataVersion>2.0.8</dataVersion>

  <ownerhistory/>

  <teamNameList/>

</cloud>
