<?xml version="1.0" encoding="UTF-8" standalone="no" ?>
<infolist>

  <version>2.0.0</version>

  <info uuid="7cad13f1d2-5b4e-7d91-dd47-fb47687843">
    <datalist key="lead">
      <data></data>
    </datalist>
    <datalist key="tag">
      <data>ComicStudio journal</data>
      <data>Seamless</data>
      <data>Sky</data>
      <data>Monochrome</data>
      <data>Star</data>
      <data>Monochromatic_pattern</data>
      <data>Background</data>
      <data>Nature</data>
    </datalist>
    <datalist key="updateHistory">
      <data></data>
    </datalist>
  </info>

</infolist>
