<?xml version="1.0" encoding="UTF-8" standalone="no" ?>
<files>

  <version>1.0.0</version>

  <file hash="" localdate="" serverdate="" versionId="">catalog.zip</file>

  <file hash="99e991b33e2d7d766e070cf73f6131052e4757f6" localdate="20201024163740" serverdate="2016/07/13 15:36:53" versionId="4J6XXInyyH_8h9KNDlHd1nqOqoDrCBqT">data/material.layer</file>

  <file hash="" localdate="" serverdate="" versionId="">externalLink</file>

  <file hash="5a26f9ce548e110034226122387a566310ddd560" localdate="20201024163740" serverdate="2016/07/13 15:36:53" versionId="RjBBfVpVkBuluj8mkad4pRsmdo4Fhpcd">icedata/layerData.xml</file>

  <file hash="" localdate="" serverdate="" versionId="">info.zip</file>

  <file hash="" localdate="" serverdate="" versionId="">modifiedData</file>

  <file hash="d87dfef20ab787b54ad1477d16a2fca85b0735b5" localdate="20201024163742" serverdate="2016/07/13 15:36:53" versionId="vChGExqqAjy4w8j5QS3QHN4ObBfpSzLm">thumbnail/thumbnail.png</file>

</files>
