<?xml version="1.0" encoding="UTF-8" standalone="no" ?>
<files>

  <version>1.0.0</version>

  <file hash="" localdate="" serverdate="" versionId="">catalog.zip</file>

  <file hash="1e6959f55b695c22c36dc129043428022e97b160" localdate="20201024170607" serverdate="2016/07/13 15:08:48" versionId="F7jrhcSWU3ZcPXSPaeF.X2azWva3lYfQ">data/material.layer</file>

  <file hash="" localdate="" serverdate="" versionId="">externalLink</file>

  <file hash="8c6d687b9771dd0ed1a2347e6b64bb9a239649a5" localdate="20201024170607" serverdate="2016/07/13 15:08:48" versionId="vptaFZxmdLnO8upvu42KCjXZZRKE5x4A">icedata/layerData.xml</file>

  <file hash="" localdate="" serverdate="" versionId="">info.zip</file>

  <file hash="" localdate="" serverdate="" versionId="">modifiedData</file>

  <file hash="5fdf2b7973607c220bb2cabdc83c92f22309a2e4" localdate="20201024170608" serverdate="2016/07/13 15:08:48" versionId="iU2cI_tTzVBib5Obz_iOijA7kJDfHEXy">thumbnail/thumbnail.png</file>

</files>
