<?xml version="1.0" encoding="UTF-8" standalone="no" ?>
<files>

  <version>1.0.0</version>

  <file hash="479ad7b8aa4b364b99c9bb963fbfa7d1997debef" localdate="20210117060432" serverdate="2021/01/01 09:13:24" versionId="G3Hddj_lyG.Bkd_fmZUx_ID2etcoxHkp">catalog.zip</file>

  <file hash="2966bbb7b678bf5932291f8eb35e1cdd2bb5e1b9" localdate="20210117060428" serverdate="2021/01/01 09:13:24" versionId="eZKXjpFtICgnzyBMipM8cLoPNE009iyl">data/material_0.layer</file>

  <file hash="" localdate="" serverdate="" versionId="">externalLink</file>

  <file hash="d4187c8a4c7485b0f07a30be4250476542089d4e" localdate="20210117060429" serverdate="2021/01/01 09:13:24" versionId="PGJBzQX.vc9diYWF_GkdoG_6W7uiagke">icedata/layerData.xml</file>

  <file hash="39ba5b217ddad7e7fd25c3f843c519e5889e3159" localdate="20210117060432" serverdate="2021/01/01 09:13:24" versionId="sKmeJd3U92ldl4dumgyR2wxR5YvllP0g">info.zip</file>

  <file hash="" localdate="" serverdate="" versionId="">modifiedData</file>

  <file hash="c9573e08a46ea42f026e77ccded040242e9dfa49" localdate="20210117060432" serverdate="2021/01/01 09:13:24" versionId="8glivw80DZvCgpq3VDnr892zwmRMl36o">thumbnail/thumbnail.png</file>

</files>
