<?xml version="1.0" encoding="UTF-8" standalone="no" ?>
<archive>

  <version>2.0.0</version>

  <catalog modify_description="0" modify_info="0" modify_name="0" modify_thumbnail="0" uuid="ebdff45ba1-c448-d9a2-fe55-a323c302e5">
    <type>material</type>
    <readonly>1</readonly>
    <share_edit_flag>0</share_edit_flag>
    <uploadable>0</uploadable>
    <tool company="celsys" name="paint" version="1.4.4"/>
    <name>nib_220</name>
    <groups>
      <group modify_description="0" modify_info="0" modify_name="0" modify_thumbnail="0" parentuuid="" uuid="97b21b8a01-4f4e-1893-f17c-b013553a43">
        <tool company="celsys" name="paint" version="1.4.4"/>
        <type ver="1.0.0">material</type>
        <name></name>
        <required>0</required>
        <reserveId>0</reserveId>
        <reserveWait>0</reserveWait>
        <items>
          <item modify_description="0" modify_info="0" modify_name="0" modify_thumbnail="0" parentuuid="" uuid="92a2540bb2-cb4a-60ad-eda8-7b48670156">
            <tool company="celsys" name="paint" version="1.4.4"/>
            <type ver="1.0.0">image</type>
            <name>nib_220</name>
            <created_date>2020/12/26 22:45:12</created_date>
            <modified_date>2020/12/26 22:45:12</modified_date>
            <required>0</required>
            <reserveId>0</reserveId>
            <reserveWait>0</reserveWait>
            <thumbnail>
              <fileref idref="bdf3d18b45-d94d-92b3-ff37-7a7c81e3e8"/>
            </thumbnail>
            <data>
              <fileref idref="75ac1b1a7d-7349-359f-4960-e34abc8bbb"/>
            </data>
            <icedata>
              <fileref idref="ff4d0281ba-1c44-73b0-73b2-d03f2a9646"/>
            </icedata>
          </item>
        </items>
      </group>
    </groups>
    <region/>
  </catalog>

  <files>
    <file document="false" encrypt="true" id="75ac1b1a7d-7349-359f-4960-e34abc8bbb" mime="application/octet-stream">
      <path>data/material_0.layer</path>
    </file>
    <file document="false" encrypt="false" id="bdf3d18b45-d94d-92b3-ff37-7a7c81e3e8" mime="image/png">
      <path>thumbnail/thumbnail.png</path>
    </file>
    <file document="false" encrypt="false" id="ff4d0281ba-1c44-73b0-73b2-d03f2a9646" mime="text/xml">
      <path>icedata/layerData.xml</path>
    </file>
  </files>

</archive>
