<?xml version="1.0" encoding="UTF-8" standalone="no" ?>
<infolist>

  <version>2.0.0</version>

  <info uuid="6d57d452a8-3949-f9bd-0ff2-2f56cd1b5d">
    <datalist key="lead">
      <data></data>
    </datalist>
    <datalist key="tag">
      <data>Seamless</data>
      <data>IllustStudio journal</data>
      <data>Color</data>
      <data>Color_pattern</data>
      <data>Background</data>
      <data>Artificial</data>
    </datalist>
    <datalist key="updateHistory">
      <data></data>
    </datalist>
  </info>

</infolist>
