<?xml version="1.0" encoding="UTF-8" standalone="no" ?>
<archive>

  <version>2.0.0</version>

  <catalog modify_description="0" modify_info="0" modify_name="0" modify_thumbnail="0" uuid="e4520f4b41-c14f-d0b1-dd6c-746c7cda80">
    <type>material</type>
    <readonly>1</readonly>
    <share_edit_flag>0</share_edit_flag>
    <uploadable>0</uploadable>
    <tool company="celsys" name="paint" version="1.1.0"/>
    <name>MM08-cloud 26</name>
    <groups>
      <group modify_description="0" modify_info="0" modify_name="0" modify_thumbnail="0" parentuuid="" uuid="64beda8a9f-af44-85b2-d01d-9a3e15525a">
        <tool company="celsys" name="paint" version="1.1.0"/>
        <type ver="1.0.0">material</type>
        <name></name>
        <required>0</required>
        <reserveId>0</reserveId>
        <reserveWait>0</reserveWait>
        <items>
          <item modify_description="0" modify_info="0" modify_name="0" modify_thumbnail="0" parentuuid="" uuid="9d339adfe9-ab4e-c5a0-e2cd-cc5d9fb768">
            <tool company="celsys" name="paint" version="1.1.0"/>
            <type ver="1.0.0">image</type>
            <name>MM08-cloud 26</name>
            <created_date>2016/06/21 10:07:39</created_date>
            <modified_date>2016/06/21 10:07:39</modified_date>
            <required>0</required>
            <permittool>
              <cspdebut>1</cspdebut>
            </permittool>
            <reserveId>0</reserveId>
            <reserveWait>0</reserveWait>
            <thumbnail>
              <fileref idref="14b6a237bd-e944-1698-3549-ea2e443e6d"/>
            </thumbnail>
            <data>
              <fileref idref="5b57ca02e6-1f42-03a4-8d4c-19fe79f064"/>
            </data>
            <icedata>
              <fileref idref="47b0df1289-604d-d5b1-4c5c-dacf6d498b"/>
            </icedata>
          </item>
        </items>
      </group>
    </groups>
    <region/>
  </catalog>

  <files>
    <file document="false" encrypt="false" id="14b6a237bd-e944-1698-3549-ea2e443e6d" mime="image/png">
      <path>thumbnail/thumbnail.png</path>
    </file>
    <file document="false" encrypt="false" id="47b0df1289-604d-d5b1-4c5c-dacf6d498b" mime="text/xml">
      <path>icedata/layerData.xml</path>
    </file>
    <file document="false" encrypt="true" id="5b57ca02e6-1f42-03a4-8d4c-19fe79f064" mime="application/octet-stream">
      <path>data/material.layer</path>
    </file>
  </files>

</archive>
