<?xml version="1.0" encoding="UTF-8" standalone="no" ?>
<files>

  <version>1.0.0</version>

  <file hash="ca412c4fbdfb6d01e75b440d2855a8db06df3917" localdate="20210117055950" serverdate="2021/01/01 09:26:43" versionId="TJ5jOJDlpA9CVzGgcgo2VVh5BSSP8QW7">catalog.zip</file>

  <file hash="6fd61c93895a1d95f0340efe6d6999551559accb" localdate="20210117055946" serverdate="2021/01/01 09:26:43" versionId="8sEbo_2w5ezXvBfI0ii5XIZ.0lmC9U4P">data/material_0.layer</file>

  <file hash="" localdate="" serverdate="" versionId="">externalLink</file>

  <file hash="d02f12b3f1d51af4958e75150108ddff7b98baa5" localdate="20210117055947" serverdate="2021/01/01 09:26:43" versionId="m4sQ1koS.zpCZdN5QH6ID__vv5tfUWV4">icedata/layerData.xml</file>

  <file hash="6207d8f6a4ddcdf3a52018c0afd486c1c7d80076" localdate="20210117055950" serverdate="2021/01/01 09:26:43" versionId="_BOmU588lFx2.kQFlpkb6wqPN1CwxfqB">info.zip</file>

  <file hash="" localdate="" serverdate="" versionId="">modifiedData</file>

  <file hash="9832bcd9b86c19dd0ce0a6e65cee71ee250e49ef" localdate="20210117055950" serverdate="2021/01/01 09:26:43" versionId="dj94.Ge9LLmr2Pkn6Po2HetvrG8e0_KF">thumbnail/thumbnail.png</file>

</files>
