<?xml version="1.0" encoding="UTF-8" standalone="no" ?>
<cloud>

  <version>1.0.0</version>

  <name>単色</name>

  <cloudcontentid>945</cloudcontentid>

  <revision>1</revision>

  <key>6b3de67860-1d40-3fa8-6c3c-e3e2112b6d</key>

  <contenttype>material</contenttype>

  <contentsubtype>image</contentsubtype>

  <thumbnailurl></thumbnailurl>

  <subpath>Paint011</subpath>

  <basePath>installation_material/45/09/945</basePath>

  <size>73991</size>

  <permit>0</permit>

  <husk>1</husk>

  <owner>9114</owner>

  <acl></acl>

  <createdat>2016-07-13 15:30:04</createdat>

  <updatedat>2016-07-13 15:30:07</updatedat>

  <dataVersion>2.0.0</dataVersion>

  <ownerhistory/>

  <teamNameList/>

</cloud>
