<?xml version="1.0" encoding="UTF-8" standalone="no" ?>
<cloud>

  <version>1.0.0</version>

  <name>ガッシュ01</name>

  <cloudcontentid>2939</cloudcontentid>

  <revision>1</revision>

  <key>0304bde642-854c-f58f-26ad-0ce64c941e</key>

  <contenttype>material</contenttype>

  <contentsubtype>image</contentsubtype>

  <thumbnailurl></thumbnailurl>

  <subpath>Paint109</subpath>

  <basePath>installation_material/39/29/2939</basePath>

  <size>89658</size>

  <permit>0</permit>

  <husk>0</husk>

  <owner>9114</owner>

  <acl></acl>

  <createdat>2019-02-28 11:08:08</createdat>

  <updatedat>2019-02-28 11:08:12</updatedat>

  <dataVersion>2.0.8</dataVersion>

  <ownerhistory/>

  <teamNameList/>

</cloud>
