<?xml version="1.0" encoding="UTF-8" standalone="no" ?>
<files>

  <version>1.0.0</version>

  <file hash="d0e60ecc1901052f0148cd8d714d59b1fc54c077" localdate="20220831212944" serverdate="2022/09/01 12:34:41" versionId="nwk4Ihd1IT8SL58qkvBceovtKqp1.ShC">catalog.zip</file>

  <file hash="a6c94d00ec6d9acae74b375bdd6c100bb1d1caf4" localdate="20220831212941" serverdate="2022/09/01 12:34:41" versionId="fmGj0u.kdlkEl21DxSMzQ3GiouGKqphQ">data/material_0.layer</file>

  <file hash="" localdate="" serverdate="" versionId="">externalLink</file>

  <file hash="231e720324ca50aba0a10ab232ad15d811426c41" localdate="20220831212942" serverdate="2022/09/01 12:34:41" versionId="OLmmiQ2hZvPv9cq8K4g60KZLn0GWtszJ">icedata/layerData.xml</file>

  <file hash="0e9d1479c3ce2ba1f2803438ede6f5d864f1fa53" localdate="20220831212944" serverdate="2022/09/01 12:34:41" versionId="KhZjmnuMCfMjtvrcz2M7f.7P.FWnFdD0">info.zip</file>

  <file hash="" localdate="" serverdate="" versionId="">modifiedData</file>

  <file hash="e3ddf4aa878da13efa2f354b7103a35662469679" localdate="20220831212944" serverdate="2022/09/01 12:34:41" versionId="dZAV4.F2OQP4hf99RhO5i_qhVR.1jxWX">thumbnail/thumbnail.png</file>

</files>
