<?xml version="1.0" encoding="UTF-8" standalone="no" ?>
<files>

  <version>1.0.0</version>

  <file hash="" localdate="" serverdate="" versionId="">catalog.zip</file>

  <file hash="17371ba988799a39f23c803a161080b8fb358be3" localdate="20210604072037" serverdate="2021/05/26 13:43:07" versionId="E6ikY2i7ZKe34fo8sr6zUjswO7U01v1U">data/material_0.layer</file>

  <file hash="" localdate="" serverdate="" versionId="">externalLink</file>

  <file hash="4b657bebac9142acc06a3410077f66f38af3ea71" localdate="20210604072038" serverdate="2021/05/26 13:43:07" versionId="FV.exxZqqZfIP54Y.a2I2XAjrnZn0gnI">icedata/layerData.xml</file>

  <file hash="" localdate="" serverdate="" versionId="">info.zip</file>

  <file hash="" localdate="" serverdate="" versionId="">modifiedData</file>

  <file hash="7584d1caf20293758d19eac158612b4863d25787" localdate="20210604072038" serverdate="2021/05/26 13:43:07" versionId="WWwU_5S6Y__A1FC3zfi7.yGY2cqeHDA2">thumbnail/thumbnail.png</file>

</files>
