<?xml version="1.0" encoding="UTF-8" standalone="no" ?>
<files>

  <version>1.0.0</version>

  <file hash="8a5af68db6ff3d3f4ece27ca3ab5e13de1b7c0c2" localdate="20220831214558" serverdate="2022/09/01 12:04:03" versionId="BQxOUT89EcaJwZoMv51kp5SPAklp4zdp">catalog.zip</file>

  <file hash="1d0d80109bcf34d754945ebcbaf71e4f64335812" localdate="20220831214554" serverdate="2022/09/01 12:04:03" versionId="7x.TBM0mQZ0a.BFKsafYlbNd4AoczxHQ">data/material_0.layer</file>

  <file hash="" localdate="" serverdate="" versionId="">externalLink</file>

  <file hash="75158142dd65eb2d947edb462b1db71f6a17bcbd" localdate="20220831214555" serverdate="2022/09/01 12:04:03" versionId="Ne13twmjbyByGhOlrAYg41f2BIlZT4u6">icedata/layerData.xml</file>

  <file hash="6742efedbb2869e649a00b054c87c5222f2329a8" localdate="20220831214558" serverdate="2022/09/01 12:04:03" versionId="QUpohepc_wRcpH8p6j4mTzbAFV0LbtR8">info.zip</file>

  <file hash="" localdate="" serverdate="" versionId="">modifiedData</file>

  <file hash="0c89e8c1e27ce4afdabb7b6b5b4e3a873ef3095c" localdate="20220831214558" serverdate="2022/09/01 12:04:03" versionId="VfKHgiJxG8gUH_KjBLMaqmZjuB73BLkc">thumbnail/thumbnail.png</file>

</files>
