<?xml version="1.0" encoding="UTF-8" standalone="no" ?>
<cloud>

  <version>1.0.0</version>

  <name>草A4</name>

  <cloudcontentid>108</cloudcontentid>

  <revision>1</revision>

  <key>9acb427f5d-3c4d-458e-6040-4cf3bf73ce</key>

  <contenttype>material</contenttype>

  <contentsubtype>image</contentsubtype>

  <thumbnailurl></thumbnailurl>

  <subpath>Paint001</subpath>

  <basePath>installation_material/08/01/108</basePath>

  <size>108112</size>

  <permit>1</permit>

  <husk>0</husk>

  <owner>9114</owner>

  <acl></acl>

  <createdat>2016-07-13 14:34:28</createdat>

  <updatedat>2016-07-13 14:34:30</updatedat>

  <dataVersion>2.0.0</dataVersion>

  <ownerhistory/>

  <teamNameList/>

</cloud>
