<?xml version="1.0" encoding="UTF-8" standalone="no" ?>
<files>

  <version>1.0.0</version>

  <file hash="7e3785ebf94c0eb2a15094831ec6c1fcd6dfcee0" localdate="20201025162513" serverdate="2020/07/18 12:52:22" versionId="l5bQRN8i2rQSfcEcgSyI4vuwyfn7S4_s">catalog.zip</file>

  <file hash="0465073fba6c0c26340ce20d9531d3c786b50d79" localdate="20201025162457" serverdate="2020/07/18 12:52:22" versionId="k2VTrJ5GM47EYs43ENKyBSmRXejVI_Cf">data/material_0.layer</file>

  <file hash="" localdate="" serverdate="" versionId="">externalLink</file>

  <file hash="71b5ca1e9ae36f8625a3e3bce6ccc4b75a41322e" localdate="20201025162505" serverdate="2020/07/18 12:52:22" versionId="cBo.X5ywyMcDvMoVObs96KHNQ.qYQRft">icedata/layerData.xml</file>

  <file hash="e42e84e480780863a840dfcb721b061c7051fbd2" localdate="20201025162513" serverdate="2020/07/18 12:52:22" versionId="SwTeHAVVjwvNBPYDMSRzi7QbrV99mUdF">info.zip</file>

  <file hash="" localdate="" serverdate="" versionId="">modifiedData</file>

  <file hash="6ca37b37a3a9c2bd6ade471c896c2572f061a532" localdate="20201025162513" serverdate="2020/07/18 12:52:22" versionId="Z3lb_Rkevm7EXSFBziV1k0Jk6VSdAYRK">thumbnail/thumbnail.png</file>

</files>
